{
  "output": {
    "gtceu__alloy_blast_smelter": [
      {
        "id": "gtceu:alloy_blast_smelter/tantalum_carbide_gas",
        "category": "gtceu:alloy_blast_smelter",
        "width": 164,
        "height": 135,
        "catalysts": [
          {
            "id": "gtceu:programmed_circuit",
            "chance": 0.0
          }
        ],
        "inputs": [
          {
            "id": "gtceu:tantalum_dust"
          },
          {
            "id": "gtceu:carbon_dust"
          },
          {
            "id": "gtceu:helium",
            "amount": 200
          }
        ],
        "outputs": [
          {
            "id": "gtceu:molten_tantalum_carbide",
            "amount": 288
          }
        ],
        "workstations": [
          "gtceu:alloy_blast_smelter"
        ]
      }
    ]
  }
}