{
  "uses": {
    "gtceu:assembler": [
      {
        "id": "gtceu:assembler/energy_hatch_16a_uv",
        "category": "gtceu:assembler",
        "dimensions": [
          164,
          125
        ],
        "eu_t": 491520,
        "inputs": [
          {
            "id": "gtceu:uv_transformer_1a"
          },
          {
            "id": "gtceu:uv_energy_input_hatch_4a"
          },
          {
            "id": "gtceu:yttrium_barium_cuprate_octal_wire",
            "amount": 2
          },
          {
            "id": "gtceu:darmstadtium_plate",
            "amount": 4
          }
        ],
        "outputs": [
          {
            "id": "gtceu:uv_energy_input_hatch_16a"
          }
        ],
        "catalysts": []
      }
    ],
    "gtceu:macerator_recycling": [
      {
        "id": "gtceu:macerator/macerate_uv_energy_input_hatch_4a",
        "category": "gtceu:macerator_recycling",
        "dimensions": [
          164,
          89
        ],
        "eu_t": 32,
        "inputs": [
          {
            "id": "gtceu:uv_energy_input_hatch_4a"
          }
        ],
        "outputs": [
          {
            "id": "gtceu:yttrium_barium_cuprate_dust",
            "amount": 4
          },
          {
            "id": "gtceu:darmstadtium_dust",
            "amount": 2
          }
        ],
        "catalysts": []
      }
    ],
    "gtceu:arc_furnace_recycling": [
      {
        "id": "gtceu:arc_furnace/arc_uv_energy_input_hatch_4a",
        "category": "gtceu:arc_furnace_recycling",
        "dimensions": [
          164,
          97
        ],
        "eu_t": 30,
        "inputs": [
          {
            "id": "gtceu:uv_energy_input_hatch_4a"
          },
          {
            "id": "gtceu:oxygen",
            "amount": 766
          }
        ],
        "outputs": [
          {
            "id": "gtceu:yttrium_barium_cuprate_ingot",
            "amount": 4
          },
          {
            "id": "gtceu:darmstadtium_ingot",
            "amount": 2
          }
        ],
        "catalysts": []
      }
    ]
  },
  "recipes": {
    "gtceu:assembler": [
      {
        "id": "gtceu:assembler/energy_hatch_4a_uv",
        "category": "gtceu:assembler",
        "dimensions": [
          164,
          125
        ],
        "eu_t": 491520,
        "inputs": [
          {
            "id": "gtceu:uv_energy_input_hatch"
          },
          {
            "id": "gtceu:yttrium_barium_cuprate_quadruple_wire",
            "amount": 2
          },
          {
            "id": "gtceu:darmstadtium_plate",
            "amount": 2
          }
        ],
        "outputs": [
          {
            "id": "gtceu:uv_energy_input_hatch_4a"
          }
        ],
        "catalysts": []
      }
    ]
  }
}