{
  "uses": {
    "minecraft:crafting": [
      {
        "id": "gtceu:shaped/ev_assembler",
        "category": "minecraft:crafting",
        "dimensions": [
          118,
          54
        ],
        "eu_t": 0,
        "inputs": [
          {
            "id": "gtceu:ev_robot_arm"
          },
          {
            "tag": "gtceu:micro_processor_computer"
          },
          {
            "id": "gtceu:ev_robot_arm"
          },
          {
            "id": "gtceu:ev_conveyor_module"
          },
          {
            "id": "gtceu:ev_machine_hull"
          },
          {
            "id": "gtceu:ev_conveyor_module"
          },
          {
            "id": "gtceu:aluminium_single_cable"
          },
          {
            "tag": "gtceu:micro_processor_computer"
          },
          {
            "id": "gtceu:aluminium_single_cable"
          }
        ],
        "outputs": [
          {
            "id": "gtceu:ev_assembler"
          }
        ],
        "catalysts": []
      },
      {
        "id": "gtceu:shaped/ev_assembler",
        "category": "minecraft:crafting",
        "dimensions": [
          118,
          54
        ],
        "eu_t": 0,
        "inputs": [
          {
            "id": "gtceu:ev_robot_arm"
          },
          {
            "tag": "gtceu:micro_processor_computer"
          },
          {
            "id": "gtceu:ev_robot_arm"
          },
          {
            "id": "gtceu:ev_conveyor_module"
          },
          {
            "id": "gtceu:ev_machine_hull"
          },
          {
            "id": "gtceu:ev_conveyor_module"
          },
          {
            "id": "gtceu:aluminium_single_cable"
          },
          {
            "tag": "gtceu:micro_processor_computer"
          },
          {
            "id": "gtceu:aluminium_single_cable"
          }
        ],
        "outputs": [
          {
            "id": "gtceu:ev_assembler"
          }
        ],
        "catalysts": []
      },
      {
        "id": "gtceu:shaped/ev_packer",
        "category": "minecraft:crafting",
        "dimensions": [
          118,
          54
        ],
        "eu_t": 0,
        "inputs": [
          {
            "tag": "minecraft:chest"
          },
          {
            "tag": "gtceu:micro_processor_computer"
          },
          {
            "tag": "minecraft:chest"
          },
          {
            "id": "gtceu:ev_robot_arm"
          },
          {
            "id": "gtceu:ev_machine_hull"
          },
          {
            "id": "gtceu:ev_conveyor_module"
          },
          {
            "id": "gtceu:aluminium_single_cable"
          },
          {
            "tag": "gtceu:micro_processor_computer"
          },
          {
            "id": "gtceu:aluminium_single_cable"
          }
        ],
        "outputs": [
          {
            "id": "gtceu:ev_packer"
          }
        ],
        "catalysts": []
      },
      {
        "id": "gtceu:shaped/ev_circuit_assembler",
        "category": "minecraft:crafting",
        "dimensions": [
          118,
          54
        ],
        "eu_t": 0,
        "inputs": [
          {
            "id": "gtceu:ev_robot_arm"
          },
          {
            "tag": "gtceu:micro_processor_mainframe"
          },
          {
            "id": "gtceu:ev_emitter"
          },
          {
            "id": "gtceu:ev_conveyor_module"
          },
          {
            "id": "gtceu:ev_machine_hull"
          },
          {
            "id": "gtceu:ev_conveyor_module"
          },
          {
            "id": "gtceu:aluminium_single_cable"
          },
          {
            "tag": "gtceu:micro_processor_mainframe"
          },
          {
            "id": "gtceu:aluminium_single_cable"
          }
        ],
        "outputs": [
          {
            "id": "gtceu:ev_circuit_assembler"
          }
        ],
        "catalysts": []
      }
    ],
    "gtceu:macerator_recycling": [
      {
        "id": "gtceu:macerator/macerate_ev_robot_arm",
        "category": "gtceu:macerator_recycling",
        "dimensions": [
          164,
          89
        ],
        "eu_t": 8,
        "inputs": [
          {
            "id": "gtceu:ev_robot_arm"
          }
        ],
        "outputs": [
          {
            "id": "gtceu:kanthal_dust",
            "amount": 12
          },
          {
            "id": "gtceu:rubber_dust",
            "amount": 11
          },
          {
            "id": "gtceu:titanium_dust",
            "amount": 9
          },
          {
            "id": "gtceu:small_aluminium_dust",
            "amount": 34
          }
        ],
        "catalysts": []
      }
    ],
    "gtceu:arc_furnace_recycling": [
      {
        "id": "gtceu:arc_furnace/arc_ev_robot_arm",
        "category": "gtceu:arc_furnace_recycling",
        "dimensions": [
          164,
          97
        ],
        "eu_t": 30,
        "inputs": [
          {
            "id": "gtceu:ev_robot_arm"
          },
          {
            "id": "gtceu:oxygen",
            "amount": 1376
          }
        ],
        "outputs": [
          {
            "id": "gtceu:kanthal_ingot",
            "amount": 12
          },
          {
            "id": "gtceu:titanium_block"
          },
          {
            "id": "gtceu:aluminium_ingot",
            "amount": 8
          },
          {
            "id": "gtceu:neodymium_nugget",
            "amount": 13
          }
        ],
        "catalysts": []
      }
    ]
  },
  "recipes": {
    "minecraft:crafting": [
      {
        "id": "gtceu:shaped/robot_arm_ev",
        "category": "minecraft:crafting",
        "dimensions": [
          118,
          54
        ],
        "eu_t": 0,
        "inputs": [
          {
            "id": "gtceu:aluminium_single_cable"
          },
          {
            "id": "gtceu:aluminium_single_cable"
          },
          {
            "id": "gtceu:aluminium_single_cable"
          },
          {
            "id": "gtceu:ev_electric_motor"
          },
          {
            "id": "gtceu:titanium_rod"
          },
          {
            "id": "gtceu:ev_electric_motor"
          },
          {
            "id": "gtceu:ev_electric_piston"
          },
          {
            "tag": "gtceu:micro_processor_computer"
          },
          {
            "id": "gtceu:titanium_rod"
          }
        ],
        "outputs": [
          {
            "id": "gtceu:ev_robot_arm"
          }
        ],
        "catalysts": []
      }
    ],
    "gtceu:assembler": [
      {
        "id": "gtceu:assembler/robot_arm_ev",
        "category": "gtceu:assembler",
        "dimensions": [
          164,
          125
        ],
        "eu_t": 30,
        "inputs": [
          {
            "id": "gtceu:aluminium_single_cable",
            "amount": 3
          },
          {
            "id": "gtceu:titanium_rod",
            "amount": 2
          },
          {
            "id": "gtceu:ev_electric_motor",
            "amount": 2
          },
          {
            "id": "gtceu:ev_electric_piston"
          },
          {
            "tag": "gtceu:micro_processor_computer"
          }
        ],
        "outputs": [
          {
            "id": "gtceu:ev_robot_arm"
          }
        ],
        "catalysts": []
      }
    ]
  }
}