{
  "output": {
    "minecraft__crafting": [
      {
        "id": "gtceu:shaped/pickaxe_titanium",
        "category": "minecraft:crafting",
        "width": 118,
        "height": 54,
        "inputs": [
          {
            "id": "gtceu:titanium_plate"
          },
          {
            "id": "gtceu:titanium_ingot"
          },
          {
            "id": "gtceu:titanium_ingot"
          },
          {
            "tag": "gtceu:iron_file"
          },
          {
            "id": "minecraft:stick"
          },
          {
            "tag": "gtceu:iron_hammer"
          },
          {
            "id": "minecraft:stick"
          }
        ],
        "outputs": [
          {
            "id": "gtceu:titanium_pickaxe"
          }
        ],
        "workstations": [
          "minecraft:crafting_table"
        ]
      }
    ]
  }
}