{
  "uses": {
    "minecraft:crafting": [
      {
        "id": "gtceu:shaped/good_circuit_board",
        "category": "minecraft:crafting",
        "dimensions": [
          118,
          54
        ],
        "eu_t": 0,
        "inputs": [
          {
            "id": "gtceu:silver_single_wire"
          },
          {
            "id": "gtceu:silver_single_wire"
          },
          {
            "id": "gtceu:silver_single_wire"
          },
          {
            "id": "gtceu:silver_single_wire"
          },
          {
            "id": "gtceu:phenolic_circuit_board"
          },
          {
            "id": "gtceu:silver_single_wire"
          },
          {
            "id": "gtceu:silver_single_wire"
          },
          {
            "id": "gtceu:silver_single_wire"
          },
          {
            "id": "gtceu:silver_single_wire"
          }
        ],
        "outputs": [
          {
            "id": "gtceu:phenolic_printed_circuit_board"
          }
        ],
        "catalysts": []
      }
    ],
    "gtceu:large_chemical_reactor": [
      {
        "id": "gtceu:large_chemical_reactor/good_circuit_board_persulfate",
        "category": "gtceu:large_chemical_reactor",
        "dimensions": [
          164,
          107
        ],
        "eu_t": 30,
        "inputs": [
          {
            "id": "gtceu:silver_foil",
            "amount": 4
          },
          {
            "id": "gtceu:phenolic_circuit_board"
          },
          {
            "id": "gtceu:sodium_persulfate",
            "amount": 200
          }
        ],
        "outputs": [
          {
            "id": "gtceu:phenolic_printed_circuit_board"
          }
        ],
        "catalysts": []
      },
      {
        "id": "gtceu:large_chemical_reactor/good_circuit_board_iron3",
        "category": "gtceu:large_chemical_reactor",
        "dimensions": [
          164,
          107
        ],
        "eu_t": 30,
        "inputs": [
          {
            "id": "gtceu:silver_foil",
            "amount": 4
          },
          {
            "id": "gtceu:phenolic_circuit_board"
          },
          {
            "id": "gtceu:iron_iii_chloride",
            "amount": 100
          }
        ],
        "outputs": [
          {
            "id": "gtceu:phenolic_printed_circuit_board"
          }
        ],
        "catalysts": []
      }
    ],
    "gtceu:chemical_reactor": [
      {
        "id": "gtceu:chemical_reactor/good_circuit_board_persulfate",
        "category": "gtceu:chemical_reactor",
        "dimensions": [
          164,
          89
        ],
        "eu_t": 30,
        "inputs": [
          {
            "id": "gtceu:silver_foil",
            "amount": 4
          },
          {
            "id": "gtceu:phenolic_circuit_board"
          },
          {
            "id": "gtceu:sodium_persulfate",
            "amount": 200
          }
        ],
        "outputs": [
          {
            "id": "gtceu:phenolic_printed_circuit_board"
          }
        ],
        "catalysts": []
      },
      {
        "id": "gtceu:chemical_reactor/good_circuit_board_iron3",
        "category": "gtceu:chemical_reactor",
        "dimensions": [
          164,
          89
        ],
        "eu_t": 30,
        "inputs": [
          {
            "id": "gtceu:silver_foil",
            "amount": 4
          },
          {
            "id": "gtceu:phenolic_circuit_board"
          },
          {
            "id": "gtceu:iron_iii_chloride",
            "amount": 100
          }
        ],
        "outputs": [
          {
            "id": "gtceu:phenolic_printed_circuit_board"
          }
        ],
        "catalysts": []
      }
    ]
  },
  "recipes": {
    "gtceu:assembler": [
      {
        "id": "gtceu:assembler/phenolic_board",
        "category": "gtceu:assembler",
        "dimensions": [
          164,
          125
        ],
        "eu_t": 30,
        "inputs": [
          {
            "id": "gtceu:wood_dust"
          },
          {
            "id": "gtceu:glue",
            "amount": 50
          }
        ],
        "outputs": [
          {
            "id": "gtceu:phenolic_circuit_board"
          }
        ],
        "catalysts": [
          {
            "id": "gtceu:programmed_circuit",
            "chance": 0.0,
            "nbt": "{Configuration:1}"
          }
        ]
      }
    ]
  }
}