{
  "recipes": {
    "minecraft:crafting": [
      {
        "id": "gtceu:shaped/stick_niobium_titanium",
        "category": "minecraft:crafting",
        "dimensions": [
          118,
          54
        ],
        "eu_t": 0,
        "inputs": [
          {
            "tag": "gtceu:tungsten_carbide_file"
          },
          {
            "id": "gtceu:niobium_titanium_ingot"
          }
        ],
        "outputs": [
          {
            "id": "gtceu:niobium_titanium_rod"
          }
        ],
        "catalysts": []
      },
      {
        "id": "gtceu:shaped/stick_long_niobium_titanium",
        "category": "minecraft:crafting",
        "dimensions": [
          118,
          54
        ],
        "eu_t": 0,
        "inputs": [
          {
            "tag": "gtceu:tungsten_carbide_buzzsaw"
          },
          {
            "id": "gtceu:long_niobium_titanium_rod"
          }
        ],
        "outputs": [
          {
            "id": "gtceu:niobium_titanium_rod",
            "amount": 2
          }
        ],
        "catalysts": []
      }
    ],
    "gtceu:lathe": [
      {
        "id": "gtceu:lathe/lathe_niobium_titanium_to_rod",
        "category": "gtceu:lathe",
        "dimensions": [
          150,
          61
        ],
        "eu_t": 16,
        "inputs": [
          {
            "id": "gtceu:niobium_titanium_ingot"
          }
        ],
        "outputs": [
          {
            "id": "gtceu:niobium_titanium_rod"
          },
          {
            "id": "gtceu:small_niobium_titanium_dust",
            "amount": 2
          }
        ],
        "catalysts": []
      }
    ],
    "gtceu:extruder": [
      {
        "id": "gtceu:extruder/extrude_niobium_titanium_to_rod",
        "category": "gtceu:extruder",
        "dimensions": [
          150,
          61
        ],
        "eu_t": 180,
        "inputs": [
          {
            "id": "gtceu:niobium_titanium_ingot"
          }
        ],
        "outputs": [
          {
            "id": "gtceu:niobium_titanium_rod",
            "amount": 2
          }
        ],
        "catalysts": [
          {
            "id": "gtceu:rod_extruder_mold",
            "chance": 0.0
          }
        ]
      }
    ],
    "gtceu:cutter": [
      {
        "id": "gtceu:cutter/cut_niobium_titanium_long_rod_to_rod_distilled_water",
        "category": "gtceu:cutter",
        "dimensions": [
          150,
          89
        ],
        "eu_t": 4,
        "inputs": [
          {
            "id": "gtceu:long_niobium_titanium_rod"
          },
          {
            "id": "gtceu:distilled_water",
            "amount": 3
          }
        ],
        "outputs": [
          {
            "id": "gtceu:niobium_titanium_rod",
            "amount": 2
          }
        ],
        "catalysts": []
      },
      {
        "id": "gtceu:cutter/cut_niobium_titanium_long_rod_to_rod_water",
        "category": "gtceu:cutter",
        "dimensions": [
          150,
          89
        ],
        "eu_t": 4,
        "inputs": [
          {
            "id": "gtceu:long_niobium_titanium_rod"
          },
          {
            "id": "minecraft:water",
            "amount": 4
          }
        ],
        "outputs": [
          {
            "id": "gtceu:niobium_titanium_rod",
            "amount": 2
          }
        ],
        "catalysts": []
      },
      {
        "id": "gtceu:cutter/cut_niobium_titanium_long_rod_to_rod",
        "category": "gtceu:cutter",
        "dimensions": [
          150,
          89
        ],
        "eu_t": 4,
        "inputs": [
          {
            "id": "gtceu:long_niobium_titanium_rod"
          },
          {
            "id": "gtceu:lubricant"
          }
        ],
        "outputs": [
          {
            "id": "gtceu:niobium_titanium_rod",
            "amount": 2
          }
        ],
        "catalysts": []
      }
    ]
  },
  "uses": {
    "minecraft:crafting": [
      {
        "id": "gtceu:shaped/bolt_saw_niobium_titanium",
        "category": "minecraft:crafting",
        "dimensions": [
          118,
          54
        ],
        "eu_t": 0,
        "inputs": [
          {
            "tag": "gtceu:tungsten_carbide_buzzsaw"
          },
          {
            "id": "gtceu:niobium_titanium_rod"
          }
        ],
        "outputs": [
          {
            "id": "gtceu:niobium_titanium_bolt",
            "amount": 2
          }
        ],
        "catalysts": []
      },
      {
        "id": "gtceu:shaped/stick_long_stick_niobium_titanium",
        "category": "minecraft:crafting",
        "dimensions": [
          118,
          54
        ],
        "eu_t": 0,
        "inputs": [
          {
            "id": "gtceu:niobium_titanium_rod"
          },
          {
            "tag": "gtceu:tungsten_carbide_hammer"
          },
          {
            "id": "gtceu:niobium_titanium_rod"
          }
        ],
        "outputs": [
          {
            "id": "gtceu:long_niobium_titanium_rod"
          }
        ],
        "catalysts": []
      },
      {
        "id": "gtceu:shaped/stick_long_stick_niobium_titanium",
        "category": "minecraft:crafting",
        "dimensions": [
          118,
          54
        ],
        "eu_t": 0,
        "inputs": [
          {
            "id": "gtceu:niobium_titanium_rod"
          },
          {
            "tag": "gtceu:tungsten_carbide_hammer"
          },
          {
            "id": "gtceu:niobium_titanium_rod"
          }
        ],
        "outputs": [
          {
            "id": "gtceu:long_niobium_titanium_rod"
          }
        ],
        "catalysts": []
      },
      {
        "id": "gtceu:shaped/spring_small_niobium_titanium",
        "category": "minecraft:crafting",
        "dimensions": [
          118,
          54
        ],
        "eu_t": 0,
        "inputs": [
          {
            "tag": "gtceu:tungsten_carbide_buzzsaw"
          },
          {
            "tag": "gtceu:tungsten_carbide_file"
          },
          {
            "id": "gtceu:niobium_titanium_rod"
          },
          {
            "tag": "gtceu:iv_tungsten_carbide_wire_cutter"
          }
        ],
        "outputs": [
          {
            "id": "gtceu:small_niobium_titanium_spring"
          }
        ],
        "catalysts": []
      }
    ],
    "gtceu:forge_hammer": [
      {
        "id": "gtceu:forge_hammer/hammer_niobium_titanium_rod_to_long_rod",
        "category": "gtceu:forge_hammer",
        "dimensions": [
          150,
          61
        ],
        "eu_t": 16,
        "inputs": [
          {
            "id": "gtceu:niobium_titanium_rod",
            "amount": 2
          }
        ],
        "outputs": [
          {
            "id": "gtceu:long_niobium_titanium_rod"
          }
        ],
        "catalysts": []
      }
    ],
    "gtceu:bender": [
      {
        "id": "gtceu:bender/bend_niobium_titanium_rod_to_small_spring",
        "category": "gtceu:bender",
        "dimensions": [
          150,
          61
        ],
        "eu_t": 7,
        "inputs": [
          {
            "id": "gtceu:niobium_titanium_rod"
          }
        ],
        "outputs": [
          {
            "id": "gtceu:small_niobium_titanium_spring",
            "amount": 2
          }
        ],
        "catalysts": [
          {
            "id": "gtceu:programmed_circuit",
            "chance": 0.0,
            "nbt": "{Configuration:1}"
          }
        ]
      }
    ],
    "gtceu:cutter": [
      {
        "id": "gtceu:cutter/cut_niobium_titanium_rod_to_bolt_distilled_water",
        "category": "gtceu:cutter",
        "dimensions": [
          150,
          89
        ],
        "eu_t": 4,
        "inputs": [
          {
            "id": "gtceu:niobium_titanium_rod"
          },
          {
            "id": "gtceu:distilled_water",
            "amount": 3
          }
        ],
        "outputs": [
          {
            "id": "gtceu:niobium_titanium_bolt",
            "amount": 4
          }
        ],
        "catalysts": []
      },
      {
        "id": "gtceu:cutter/cut_niobium_titanium_rod_to_bolt",
        "category": "gtceu:cutter",
        "dimensions": [
          150,
          89
        ],
        "eu_t": 4,
        "inputs": [
          {
            "id": "gtceu:niobium_titanium_rod"
          },
          {
            "id": "gtceu:lubricant"
          }
        ],
        "outputs": [
          {
            "id": "gtceu:niobium_titanium_bolt",
            "amount": 4
          }
        ],
        "catalysts": []
      },
      {
        "id": "gtceu:cutter/cut_niobium_titanium_rod_to_bolt_water",
        "category": "gtceu:cutter",
        "dimensions": [
          150,
          89
        ],
        "eu_t": 4,
        "inputs": [
          {
            "id": "gtceu:niobium_titanium_rod"
          },
          {
            "id": "minecraft:water",
            "amount": 4
          }
        ],
        "outputs": [
          {
            "id": "gtceu:niobium_titanium_bolt",
            "amount": 4
          }
        ],
        "catalysts": []
      }
    ],
    "gtceu:macerator_recycling": [
      {
        "id": "gtceu:macerator/macerate_niobium_titanium_rod",
        "category": "gtceu:macerator_recycling",
        "dimensions": [
          164,
          89
        ],
        "eu_t": 32,
        "inputs": [
          {
            "id": "gtceu:niobium_titanium_rod"
          }
        ],
        "outputs": [
          {
            "id": "gtceu:small_niobium_titanium_dust",
            "amount": 2
          }
        ],
        "catalysts": []
      }
    ],
    "gtceu:extractor_recycling": [
      {
        "id": "gtceu:extractor/extract_niobium_titanium_rod",
        "category": "gtceu:extractor_recycling",
        "dimensions": [
          150,
          79
        ],
        "eu_t": 480,
        "inputs": [
          {
            "id": "gtceu:niobium_titanium_rod"
          }
        ],
        "outputs": [
          {
            "id": "gtceu:niobium_titanium",
            "amount": 72
          }
        ],
        "catalysts": []
      }
    ],
    "gtceu:arc_furnace_recycling": [
      {
        "id": "gtceu:arc_furnace/arc_niobium_titanium_rod",
        "category": "gtceu:arc_furnace_recycling",
        "dimensions": [
          164,
          97
        ],
        "eu_t": 30,
        "inputs": [
          {
            "id": "gtceu:niobium_titanium_rod"
          },
          {
            "id": "gtceu:oxygen",
            "amount": 31
          }
        ],
        "outputs": [
          {
            "id": "gtceu:niobium_titanium_nugget",
            "amount": 4
          }
        ],
        "catalysts": []
      }
    ]
  }
}